mhtml_converter/__init__.py
mhtml_converter/__main__.py
mhtml_converter/cli.py
mhtml_converter/converter.py
mhtml_converter/bin/mhtml-to-html-darwin-amd64
mhtml_converter/bin/mhtml-to-html-darwin-arm64
mhtml_converter/bin/mhtml-to-html-linux-amd64
mhtml_converter/bin/mhtml-to-html-linux-arm64
mhtml_converter/bin/mhtml-to-html-windows-amd64.exe
mhtml_to_html_py-1.1.0.data/data/mhtml_converter/bin/mhtml-to-html-darwin-amd64
mhtml_to_html_py-1.1.0.data/data/mhtml_converter/bin/mhtml-to-html-darwin-arm64
mhtml_to_html_py-1.1.0.data/data/mhtml_converter/bin/mhtml-to-html-linux-amd64
mhtml_to_html_py-1.1.0.data/data/mhtml_converter/bin/mhtml-to-html-linux-arm64
mhtml_to_html_py-1.1.0.data/data/mhtml_converter/bin/mhtml-to-html-windows-amd64.exe
mhtml_to_html_py-1.1.0.dist-info/METADATA
mhtml_to_html_py-1.1.0.dist-info/WHEEL
mhtml_to_html_py-1.1.0.dist-info/entry_points.txt
mhtml_to_html_py-1.1.0.dist-info/licenses/LICENSE
mhtml_to_html_py-1.1.0.dist-info/RECORD
