Metadata-Version: 2.4
Name: mhtml-to-html-py
Version: 1.1.0
Summary: Python wrapper for mhtml-to-html Go tool with automatic encoding detection
Project-URL: Homepage, https://github.com/mpr1255/mhtml-to-html-py
Project-URL: Repository, https://github.com/mpr1255/mhtml-to-html-py
Project-URL: Issues, https://github.com/mpr1255/mhtml-to-html-py/issues
Project-URL: Original Go Tool, https://github.com/gonejack/mhtml-to-html
Author-email: mpr1255 <mpr1255@users.noreply.github.com>
License-Expression: MIT
License-File: LICENSE
Keywords: chinese,conversion,encoding,gb18030,gbk,gonejack,html,japanese,korean,mhtml
Classifier: Development Status :: 4 - Beta
Classifier: Intended Audience :: Developers
Classifier: License :: OSI Approved :: MIT License
Classifier: Operating System :: OS Independent
Classifier: Programming Language :: Python :: 3
Classifier: Programming Language :: Python :: 3.8
Classifier: Programming Language :: Python :: 3.9
Classifier: Programming Language :: Python :: 3.10
Classifier: Programming Language :: Python :: 3.11
Classifier: Programming Language :: Python :: 3.12
Classifier: Topic :: Text Processing :: Markup :: HTML
Classifier: Topic :: Utilities
Requires-Python: >=3.8
Provides-Extra: test
Requires-Dist: pytest-cov>=3.0; extra == 'test'
Requires-Dist: pytest>=6.0; extra == 'test'
